{
  "Layers": [
    {
      "Instances": [
        {
          "Weights": [
            -9.7413300397887621,
            4.50325861690454
          ],
          "Threshold": 4.5059002504532746
        },
        {
          "Weights": [
            -0.9252732546486172,
            -0.97722926082476613
          ],
          "Threshold": -0.0413513413464092
        },
        {
          "Weights": [
            5.418200217802057,
            -3.5954126437474074
          ],
          "Threshold": 1.64836169065675
        },
        {
          "Weights": [
            -3.1155122832757711,
            3.5419112638621142
          ],
          "Threshold": -0.46383246399161815
        }
      ]
    },
    {
      "Instances": [
        {
          "Weights": [
            27.618264720252157,
            1.2641479790083634,
            4.6926131015102133,
            -10.275612374916156
          ],
          "Threshold": -0.080273793864321027
        }
      ]
    }
  ]
}